topsis_prabhpreet_102303258/__init__.py
topsis_prabhpreet_102303258/topsis.py
topsis_prabhpreet_102303258-0.1.0.dist-info/licenses/LICENSE
topsis_prabhpreet_102303258-0.1.0.dist-info/METADATA
topsis_prabhpreet_102303258-0.1.0.dist-info/WHEEL
topsis_prabhpreet_102303258-0.1.0.dist-info/entry_points.txt
topsis_prabhpreet_102303258-0.1.0.dist-info/top_level.txt
topsis_prabhpreet_102303258-0.1.0.dist-info/RECORD
