Metadata-Version: 2.4
Name: Topsis-Prabhpreet-102303258
Version: 0.1.0
Summary: A command line implementation of TOPSIS
Author: Prabhpreet Singh
License: MIT
Requires-Python: >=3.8
License-File: LICENSE
Requires-Dist: pandas
Requires-Dist: numpy
Dynamic: license-file
